rest_tester/__init__.py
rest_tester/core/__init__.py
rest_tester/core/application_manager.py
rest_tester/core/config_locator.py
rest_tester/core/service_facade.py
rest_tester/core/validation_service.py
rest_tester/gui_model/__init__.py
rest_tester/gui_model/base_instance_widget.py
rest_tester/gui_model/client_instance_gui.py
rest_tester/gui_model/defaults_widget.py
rest_tester/gui_model/form_field_factory.py
rest_tester/gui_model/instances_gui.py
rest_tester/gui_model/log_widget.py
rest_tester/gui_model/model.py
rest_tester/gui_model/server_instance_gui.py
rest_tester/gui_model/validate.py
rest_tester/main.py
rest_tester/resources/config.yaml
rest_tester/service/__init__.py
rest_tester/service/endpoint_utils.py
rest_tester/service/logging_config.py
rest_tester/service/rest_client_manager.py
rest_tester/service/rest_server_manager.py
rest_tester-1.0.0.dist-info/LICENSE
rest_tester-1.0.0.dist-info/METADATA
rest_tester-1.0.0.dist-info/WHEEL
rest_tester-1.0.0.dist-info/entry_points.txt
rest_tester-1.0.0.dist-info/RECORD
