Metadata-Version: 2.3
Name: rest-tester
Version: 1.0.0
Summary: Test Application für REST APIs (Server and Client)
License: MIT
Keywords: rest,api,testing,server,client
Author: David Kracht
Author-email: david.kracht@mail.de
Requires-Python: >=3.9,<3.14
Classifier: Development Status :: 4 - Beta
Classifier: Intended Audience :: Developers
Classifier: License :: OSI Approved :: MIT License
Classifier: Operating System :: OS Independent
Classifier: Programming Language :: Python :: 3
Classifier: Programming Language :: Python :: 3.9
Classifier: Programming Language :: Python :: 3.10
Classifier: Programming Language :: Python :: 3.11
Classifier: Programming Language :: Python :: 3.12
Classifier: Programming Language :: Python :: 3.13
Classifier: Topic :: Internet :: WWW/HTTP :: HTTP Servers
Classifier: Topic :: Software Development :: Testing
Requires-Dist: PySide6 (>=6.7.0,<7.0.0)
Requires-Dist: flask (>=3.0.3,<4.0.0)
Requires-Dist: jinja2 (>=3.1.0,<4.0.0)
Requires-Dist: pyyaml (>=6.0.1,<7.0.0)
Requires-Dist: requests (>=2.32.4,<3.0.0)
Requires-Dist: rfc3986 (>=2.0.0,<3.0.0)
Requires-Dist: ruamel-yaml (>=0.18.6,<0.19.0)
Requires-Dist: werkzeug (>=3.0.3,<4.0.0)
Project-URL: Homepage, https://github.com/david-kracht/rest-tester
Project-URL: Repository, https://github.com/david-kracht/rest-tester
